sjk/__init__.py
sjk/asir.py
sjk/cas_kernel.py
sjk/console.py
sjk/gap.py
sjk/macaulay2.py
sjk/mathematica.py
sjk/singular.py
sjk/syntax/__init__.py
sjk/syntax/asir.py
sjk/syntax/gap.py
sjk/syntax/singular.py
sjk-0.6.1.data/data/share/jupyter/kernels/sjk-asir/kernel.json.disabled
sjk-0.6.1.data/data/share/jupyter/kernels/sjk-asir/logo-64x64.png
sjk-0.6.1.data/data/share/jupyter/kernels/sjk-gap/kernel.json
sjk-0.6.1.data/data/share/jupyter/kernels/sjk-gap/logo-64x64.png
sjk-0.6.1.data/data/share/jupyter/kernels/sjk-macaulay2/kernel.json
sjk-0.6.1.data/data/share/jupyter/kernels/sjk-macaulay2/logo-64x64.png
sjk-0.6.1.data/data/share/jupyter/kernels/sjk-mathematica/kernel.json.disabled
sjk-0.6.1.data/data/share/jupyter/kernels/sjk-mathematica/logo-64x64.png
sjk-0.6.1.data/data/share/jupyter/kernels/sjk-singular/kernel.json
sjk-0.6.1.data/data/share/jupyter/kernels/sjk-singular/logo-128x128.png
sjk-0.6.1.data/data/share/jupyter/kernels/sjk-singular/logo-64x64.png
sjk-0.6.1.dist-info/LICENSE.txt
sjk-0.6.1.dist-info/METADATA
sjk-0.6.1.dist-info/WHEEL
sjk-0.6.1.dist-info/top_level.txt
sjk-0.6.1.dist-info/RECORD
