Metadata-Version: 2.1
Name: sjk
Version: 0.6.1
Summary: SJK: Some Jupyter Kernels.
Home-page: https://github.com/roidocampo/sjk
Author: Roi Docampo
License: MIT
Classifier: Development Status :: 4 - Beta
Classifier: Framework :: Jupyter
Classifier: Intended Audience :: Developers
Classifier: Intended Audience :: Science/Research
Classifier: License :: OSI Approved :: MIT License
Classifier: Programming Language :: Python :: 3
Classifier: Programming Language :: Python :: 3.5
Classifier: Programming Language :: Python :: 3.6
Classifier: Topic :: Scientific/Engineering
Classifier: Topic :: Software Development
Requires-Python: >=3.5
License-File: LICENSE.txt
Requires-Dist: ipykernel
